LICENSE
MANIFEST.in
README.md
lastopt.py
setup.py
lastopt.egg-info/PKG-INFO
lastopt.egg-info/SOURCES.txt
lastopt.egg-info/dependency_links.txt
lastopt.egg-info/top_level.txt