Metadata-Version: 1.0
Name: lastopt
Version: 0.0.2
Summary: lastopt is a Python utility for quickly creating command line utilities using
Home-page: https://github.com/cablehead/lastopt
Author: Andy Gayton
Author-email: andy@thecablelounge.com
License: MIT
Platform: UNKNOWN
